qbuki/__init__.py
qbuki/gpt.py
qbuki/grassmannian.py
qbuki/operators.py
qbuki/povm_utils.py
qbuki/qplex.py
qbuki/random.py
qbuki/rics.py
qbuki/sics.py
qbuki/spin.py
qbuki/utils.py
qbuki/weyl_heisenberg.py
qbuki/optimize/__init__.py
qbuki/optimize/meffs.py
qbuki/optimize/quantumness.py
qbuki/sic_povms/.DS_Store
qbuki/sic_povms/d10.txt
qbuki/sic_povms/d100.txt
qbuki/sic_povms/d101.txt
qbuki/sic_povms/d102.txt
qbuki/sic_povms/d103.txt
qbuki/sic_povms/d104.txt
qbuki/sic_povms/d105.txt
qbuki/sic_povms/d106.txt
qbuki/sic_povms/d107.txt
qbuki/sic_povms/d108.txt
qbuki/sic_povms/d109.txt
qbuki/sic_povms/d11.txt
qbuki/sic_povms/d110.txt
qbuki/sic_povms/d111.txt
qbuki/sic_povms/d112.txt
qbuki/sic_povms/d113.txt
qbuki/sic_povms/d114.txt
qbuki/sic_povms/d115.txt
qbuki/sic_povms/d116.txt
qbuki/sic_povms/d117.txt
qbuki/sic_povms/d118.txt
qbuki/sic_povms/d119.txt
qbuki/sic_povms/d12.txt
qbuki/sic_povms/d120.txt
qbuki/sic_povms/d121.txt
qbuki/sic_povms/d122.txt
qbuki/sic_povms/d123.txt
qbuki/sic_povms/d124.txt
qbuki/sic_povms/d125.txt
qbuki/sic_povms/d126.txt
qbuki/sic_povms/d127.txt
qbuki/sic_povms/d128.txt
qbuki/sic_povms/d129.txt
qbuki/sic_povms/d13.txt
qbuki/sic_povms/d130.txt
qbuki/sic_povms/d131.txt
qbuki/sic_povms/d132.txt
qbuki/sic_povms/d133.txt
qbuki/sic_povms/d134.txt
qbuki/sic_povms/d135.txt
qbuki/sic_povms/d136.txt
qbuki/sic_povms/d137.txt
qbuki/sic_povms/d138.txt
qbuki/sic_povms/d139.txt
qbuki/sic_povms/d14.txt
qbuki/sic_povms/d140.txt
qbuki/sic_povms/d141.txt
qbuki/sic_povms/d142.txt
qbuki/sic_povms/d143.txt
qbuki/sic_povms/d144.txt
qbuki/sic_povms/d145.txt
qbuki/sic_povms/d146.txt
qbuki/sic_povms/d147.txt
qbuki/sic_povms/d148.txt
qbuki/sic_povms/d149.txt
qbuki/sic_povms/d15.txt
qbuki/sic_povms/d150.txt
qbuki/sic_povms/d151.txt
qbuki/sic_povms/d16.txt
qbuki/sic_povms/d17.txt
qbuki/sic_povms/d18.txt
qbuki/sic_povms/d19.txt
qbuki/sic_povms/d2.txt
qbuki/sic_povms/d20.txt
qbuki/sic_povms/d21.txt
qbuki/sic_povms/d22.txt
qbuki/sic_povms/d23.txt
qbuki/sic_povms/d24.txt
qbuki-0.1.9.dist-info/METADATA
qbuki-0.1.9.dist-info/WHEEL
qbuki-0.1.9.dist-info/top_level.txt
qbuki-0.1.9.dist-info/RECORD
