Metadata-Version: 2.1
Name: qbuki
Version: 0.1.9
Summary: QBism for Python
Home-page: https://github.com/heyredhat/qbuki
Author: Matthew Weiss
Author-email: heyredhat@gmail.com
